airless/captcha/__init__.py
airless/captcha/providers/__init__.py
airless/captcha/providers/two_captcha.py
airless_captcha-0.3.0.dist-info/METADATA
airless_captcha-0.3.0.dist-info/WHEEL
airless_captcha-0.3.0.dist-info/top_level.txt
airless_captcha-0.3.0.dist-info/RECORD
