Metadata-Version: 2.4
Name: airless-captcha
Version: 0.3.0
Summary: Airless Captcha is a package that resolve captcha challenge and based on airless framework
License: MIT License
Project-URL: Homepage, https://github.com/astercapital/airless
Project-URL: Bug Tracker, https://github.com/astercapital/airless/issues
Requires-Python: >=3.9
Requires-Dist: airless-core>=0.2.1
